[
  {
    "Site": "SportsCapping",
    "League": "NCAA-B",
    "Date": "Dec 29, 2025",
    "Matchup": "Oakland vs Wright State",
    "Service": "Sal Michaels",
    "Pick": "Oakland +3 -110 at Ace",
    "Analysis": "Free Play on Oakland +3 -110",
    "RunDate": "2025-12-29",
    "PageNum": 1
  },
  {
    "Site": "SportsCapping",
    "League": "NCAA-B",
    "Date": "Dec 29, 2025",
    "Matchup": "IU Indianapolis vs Cleveland State",
    "Service": "Black Widow",
    "Pick": "OVER 176 -115",
    "Analysis": "1* Free Wiseguy Play on IU Indianapolis/Cleveland State over 176 -115",
    "RunDate": "2025-12-29",
    "PageNum": 1
  },
  {
    "Site": "SportsCapping",
    "League": "NCAA-B",
    "Date": "Dec 29, 2025",
    "Matchup": "Long Island vs Georgia",
    "Service": "Joe Duffy",
    "Pick": "Long Island +31&frac12; -110 at Bovada",
    "Analysis": "This play targets a profitable long-term angle: large underdogs facing an opponent that drew 15 or more fouls in its previous game, provided that opponent did not lead by 20 or more at halftime last t",
    "RunDate": "2025-12-29",
    "PageNum": 1
  },
  {
    "Site": "SportsCapping",
    "League": "NCAA-B",
    "Date": "Dec 29, 2025",
    "Matchup": "Oakland vs Wright State",
    "Service": "Dustin Hawkins",
    "Pick": "Wright State -3 -110 at circa",
    "Analysis": "1 Dimer on Wright State -3 -110",
    "RunDate": "2025-12-29",
    "PageNum": 1
  },
  {
    "Site": "SportsCapping",
    "League": "NCAA-B",
    "Date": "Dec 29, 2025",
    "Matchup": "Oakland vs Wright State",
    "Service": "Max Chase",
    "Pick": "Wright State -3 -110 at Buckeye",
    "Analysis": "1* Free Pick on Wright State -3",
    "RunDate": "2025-12-29",
    "PageNum": 1
  },
  {
    "Site": "SportsCapping",
    "League": "NBA",
    "Date": "Dec 29, 2025",
    "Matchup": "Bucks vs Hornets",
    "Service": "Brian Bitler",
    "Pick": "Hornets +3&frac12; -112 at Draft Kings",
    "Analysis": "### Monday's Top Free NBA Pick",
    "RunDate": "2025-12-29",
    "PageNum": 1
  },
  {
    "Site": "SportsCapping",
    "League": "NBA",
    "Date": "Dec 29, 2025",
    "Matchup": "Bucks vs Hornets",
    "Service": "Dave Price",
    "Pick": "OVER 227&frac12; -115",
    "Analysis": "Dave's Monday Free Play:",
    "RunDate": "2025-12-29",
    "PageNum": 1
  },
  {
    "Site": "SportsCapping",
    "League": "NCAA-B",
    "Date": "Dec 29, 2025",
    "Matchup": "UTEP vs Louisiana Tech",
    "Service": "Matt Sullivan",
    "Pick": "UTEP +3&frac12; -110 at PlayMGM",
    "Analysis": "1* Bet on UTEP +3&frac12;",
    "RunDate": "2025-12-29",
    "PageNum": 1
  },
  {
    "Site": "SportsCapping",
    "League": "NCAA-B",
    "Date": "Dec 29, 2025",
    "Matchup": "New Orleans vs UT-Rio Grande Valley",
    "Service": "Sean Murphy",
    "Pick": "New Orleans +4 -110 at betonline",
    "Analysis": "Monday CBB Free play. My selection is on New Orleans plus the points over UT-Rio Grande Valley at 7:30 pm et on Monday.",
    "RunDate": "2025-12-29",
    "PageNum": 1
  },
  {
    "Site": "SportsCapping",
    "League": "NCAA-B",
    "Date": "Dec 29, 2025",
    "Matchup": "UTEP vs Louisiana Tech",
    "Service": "Mike Williams",
    "Pick": "UTEP +3&frac12; -112 at Jazz",
    "Analysis": "1* on UTEP +3&frac12;",
    "RunDate": "2025-12-29",
    "PageNum": 1
  },
  {
    "Site": "SportsCapping",
    "League": "NBA",
    "Date": "Dec 29, 2025",
    "Matchup": "Magic vs Raptors",
    "Service": "Jack Jones",
    "Pick": "Magic -1&frac12; -105 at Draft Kings",
    "Analysis": "Jack's Free Pick Monday: Orlando Magic -1.5",
    "RunDate": "2025-12-29",
    "PageNum": 1
  },
  {
    "Site": "SportsCapping",
    "League": "NBA",
    "Date": "Dec 29, 2025",
    "Matchup": "Nuggets vs Heat",
    "Service": "Jeff Alexander",
    "Pick": "Nuggets -2 -110 at circa",
    "Analysis": "1* NBA - Nuggets/Heat FREE PICK on Nuggets -2",
    "RunDate": "2025-12-29",
    "PageNum": 1
  },
  {
    "Site": "SportsCapping",
    "League": "NBA",
    "Date": "Dec 29, 2025",
    "Matchup": "Nuggets vs Heat",
    "Service": "John Martin",
    "Pick": "Heat +2&frac12; -110 at circa",
    "Analysis": "1 Unit FREE PLAY on Miami Heat +2.5",
    "RunDate": "2025-12-29",
    "PageNum": 1
  },
  {
    "Site": "SportsCapping",
    "League": "NBA",
    "Date": "Dec 29, 2025",
    "Matchup": "Hawks vs Thunder",
    "Service": "Info Plays",
    "Pick": "Thunder -13 -105 at Ace",
    "Analysis": "1* FREE INFO PLAY Thunder -13 -105",
    "RunDate": "2025-12-29",
    "PageNum": 1
  },
  {
    "Site": "SportsCapping",
    "League": "NBA",
    "Date": "Dec 29, 2025",
    "Matchup": "Wolves vs Bulls",
    "Service": "Marc David",
    "Pick": "UNDER 240 -110",
    "Analysis": "David's NBA Free Pick",
    "RunDate": "2025-12-29",
    "PageNum": 1
  },
  {
    "Site": "SportsCapping",
    "League": "NBA",
    "Date": "Dec 29, 2025",
    "Matchup": "Cavs vs Spurs",
    "Service": "Mike Lundin",
    "Pick": "Spurs -3&frac12; -112 at Draft Kings",
    "Analysis": "Cavaliers vs Spurs NBA Free Pick",
    "RunDate": "2025-12-29",
    "PageNum": 1
  },
  {
    "Site": "SportsCapping",
    "League": "NBA",
    "Date": "Dec 29, 2025",
    "Matchup": "Pacers vs Rockets",
    "Service": "Alex Smart",
    "Pick": "Pacers +15&frac12; -110 at Bovada",
    "Analysis": "The Houston Rockets enter Monday's matchup at Toyota Center as heavy favorites, laying a hefty 15.5-point spread against the struggling Indiana Pacers. At first glance, this looks like a classic misma",
    "RunDate": "2025-12-29",
    "PageNum": 1
  },
  {
    "Site": "SportsCapping",
    "League": "NBA",
    "Date": "Dec 29, 2025",
    "Matchup": "Cavs vs Spurs",
    "Service": "Brandon Lee",
    "Pick": "Spurs -2&frac12; -115 at PlayMGM",
    "Analysis": "Monday's NBA Free Pick",
    "RunDate": "2025-12-29",
    "PageNum": 1
  },
  {
    "Site": "SportsCapping",
    "League": "NFL",
    "Date": "Dec 29, 2025",
    "Matchup": "Rams vs Falcons",
    "Service": "Jimmy Boyd",
    "Pick": "UNDER 49&frac12; -110",
    "Analysis": "1* Free Pick on Rams/Falcons: under 49½",
    "RunDate": "2025-12-29",
    "PageNum": 1
  },
  {
    "Site": "SportsCapping",
    "League": "NFL",
    "Date": "Dec 29, 2025",
    "Matchup": "Rams vs Falcons",
    "Service": "Steve Janus",
    "Pick": "Falcons +7&frac12; -110 at Buckeye",
    "Analysis": "1* Free Sharp Play on Falcons +7&frac12; -110",
    "RunDate": "2025-12-29",
    "PageNum": 1
  },
  {
    "Site": "SportsCapping",
    "League": "NFL",
    "Date": "Dec 29, 2025",
    "Matchup": "Rams vs Falcons",
    "Service": "Timothy Black",
    "Pick": "Falcons +7&frac12; -115 at PlayMGM",
    "Analysis": "1* Best Bet on Falcons +7&frac12;",
    "RunDate": "2025-12-29",
    "PageNum": 1
  },
  {
    "Site": "SportsCapping",
    "League": "NFL",
    "Date": "Dec 29, 2025",
    "Matchup": "Rams vs Falcons",
    "Service": "Hunter Price",
    "Pick": "OVER 49 -110",
    "Analysis": "1* Free Pick on Rams/Falcons over 49 -110",
    "RunDate": "2025-12-29",
    "PageNum": 1
  },
  {
    "Site": "SportsCapping",
    "League": "NFL",
    "Date": "Dec 29, 2025",
    "Matchup": "Rams vs Falcons",
    "Service": "Brody Vaughn",
    "Pick": "UNDER 49&frac12; -110",
    "Analysis": "1* Free Play on under 49&frac12;",
    "RunDate": "2025-12-29",
    "PageNum": 1
  },
  {
    "Site": "SportsCapping",
    "League": "NHL",
    "Date": "Dec 29, 2025",
    "Matchup": "Wild vs Golden Knights",
    "Service": "Kenny Walker",
    "Pick": "Golden Knights -112 at circa",
    "Analysis": "Free Pick on Golden Knights -112",
    "RunDate": "2025-12-29",
    "PageNum": 1
  },
  {
    "Site": "SportsCapping",
    "League": "NBA",
    "Date": "Dec 29, 2025",
    "Matchup": "Mavs vs Blazers",
    "Service": "Ricky Tran",
    "Pick": "Mavs +1&frac12; -105 at Bovada",
    "Analysis": "Ricky's 1* play on DAL. Key Angle: It's important to remember that Ricky never makes a bet on any game based on just one angle. In order to make the grade, all his premium picks must meet several impo",
    "RunDate": "2025-12-29",
    "PageNum": 1
  }
]